haunted/__init__.py
haunted/__main__.py
haunted/cli/__init__.py
haunted/cli/main.py
haunted/core/__init__.py
haunted/core/claude_wrapper.py
haunted/core/database.py
haunted/core/git_manager.py
haunted/core/workflow.py
haunted/daemon/__init__.py
haunted/daemon/service.py
haunted/daemon/service_updated.py
haunted/mcp/__init__.py
haunted/mcp/tools.py
haunted/models/__init__.py
haunted/models/base.py
haunted/models/comment.py
haunted/models/issue.py
haunted/models/phase.py
haunted/models/task.py
haunted/models/test_result.py
haunted/utils/__init__.py
haunted/utils/config.py
haunted/utils/logger.py
haunted-0.2.0.dist-info/METADATA
haunted-0.2.0.dist-info/WHEEL
haunted-0.2.0.dist-info/entry_points.txt
haunted-0.2.0.dist-info/licenses/LICENSE
haunted-0.2.0.dist-info/RECORD
