Metadata-Version: 2.4
Name: haunted
Version: 0.2.0
Summary: 👻 Spectral Software Solutions - Your codebase just got possessed by supernatural development powers
Project-URL: Homepage, https://github.com/progcat/haunted
Project-URL: Repository, https://github.com/progcat/haunted
Project-URL: Issues, https://github.com/progcat/haunted/issues
Project-URL: Documentation, https://github.com/progcat/haunted/blob/main/README.md
Author-email: ProgCat <progcat@protonmail.com>
License-Expression: MIT
License-File: LICENSE
Keywords: ai,automation,claude,development,haunted,spectral,workflow
Classifier: Development Status :: 4 - Beta
Classifier: Intended Audience :: Developers
Classifier: License :: OSI Approved :: MIT License
Classifier: Operating System :: OS Independent
Classifier: Programming Language :: Python :: 3
Classifier: Programming Language :: Python :: 3.10
Classifier: Programming Language :: Python :: 3.11
Classifier: Programming Language :: Python :: 3.12
Classifier: Topic :: Software Development
Classifier: Topic :: Software Development :: Code Generators
Classifier: Topic :: Software Development :: Libraries :: Python Modules
Requires-Python: >=3.10
Requires-Dist: aiofiles>=23.0.0
Requires-Dist: aiosqlite>=0.19.0
Requires-Dist: claude-code-sdk
Requires-Dist: click>=8.1.0
Requires-Dist: gitpython>=3.1.0
Requires-Dist: pydantic>=2.0.0
Requires-Dist: python-dotenv>=1.0.0
Requires-Dist: pyyaml>=6.0
Requires-Dist: rich>=13.0.0
Requires-Dist: sqlmodel>=0.0.14
